nonebot_plugin_talk_with_eop_ai/__init__.py
nonebot_plugin_talk_with_eop_ai/config.py
nonebot_plugin_talk_with_eop_ai/matchers.py
nonebot_plugin_talk_with_eop_ai/rules.py
nonebot_plugin_talk_with_eop_ai/utils.py
nonebot_plugin_talk_with_eop_ai-0.1.0.dist-info/METADATA
nonebot_plugin_talk_with_eop_ai-0.1.0.dist-info/WHEEL
nonebot_plugin_talk_with_eop_ai-0.1.0.dist-info/RECORD
