Metadata-Version: 2.1
Name: nonebot-plugin-talk-with-eop-ai
Version: 0.1.0
Summary: Nonebot2 一款调用eop api的AI聊天插件
Home-page: https://github.com/nikissXI/nonebot_plugins/tree/main/nonebot_plugin_talk_with_eop_ai
License: MIT
Author: nikissXI
Author-email: 1299577815@qq.com
Requires-Python: >=3.8
Classifier: License :: OSI Approved :: MIT License
Classifier: Programming Language :: Python :: 3
Classifier: Programming Language :: Python :: 3.8
Classifier: Programming Language :: Python :: 3.9
Classifier: Programming Language :: Python :: 3.10
Classifier: Programming Language :: Python :: 3.11
Requires-Dist: httpx (>=0.24.0)
Requires-Dist: nonebot-adapter-onebot (>=2.0.0)
Requires-Dist: nonebot-plugin-htmlrender (>=0.2.1)
Requires-Dist: nonebot2 (>=2.0.0rc1)
Project-URL: Documentation, https://github.com/nikissXI/nonebot_plugins/tree/main/nonebot_plugin_talk_with_eop_ai#README.md
Project-URL: Repository, https://github.com/nikissXI/nonebot_plugins/tree/main/nonebot_plugin_talk_with_eop_ai
